[
  {
    "00": 497,
    "11": 468,
    "10": 18,
    "01": 17
  },
  {
    "01": 496,
    "10": 468,
    "00": 33,
    "11": 3
  },
  {
    "01": 263,
    "00": 248,
    "10": 253,
    "11": 236
  },
  {
    "10": 233,
    "01": 248,
    "00": 282,
    "11": 237
  },
  {
    "00": 26,
    "01": 483,
    "10": 476,
    "11": 15
  },
  {
    "00": 502,
    "11": 461,
    "10": 20,
    "01": 17
  },
  {
    "11": 213,
    "10": 231,
    "00": 253,
    "01": 303
  },
  {
    "01": 287,
    "11": 225,
    "10": 261,
    "00": 227
  },
  {
    "00": 265,
    "11": 210,
    "01": 276,
    "10": 249
  },
  {
    "00": 229,
    "11": 224,
    "10": 274,
    "01": 273
  },
  {
    "11": 443,
    "00": 520,
    "01": 10,
    "10": 27
  },
  {
    "10": 261,
    "01": 255,
    "11": 235,
    "00": 249
  },
  {
    "00": 293,
    "01": 246,
    "11": 213,
    "10": 248
  },
  {
    "01": 262,
    "11": 208,
    "00": 271,
    "10": 259
  },
  {
    "00": 248,
    "10": 257,
    "11": 234,
    "01": 261
  },
  {
    "01": 470,
    "10": 498,
    "00": 24,
    "11": 8
  },
  {
    "01": 82,
    "00": 522,
    "11": 302,
    "10": 94
  },
  {
    "01": 280,
    "10": 534,
    "00": 105,
    "11": 81
  },
  {
    "10": 303,
    "00": 339,
    "11": 168,
    "01": 190
  },
  {
    "10": 325,
    "00": 297,
    "11": 193,
    "01": 185
  },
  {
    "10": 290,
    "01": 513,
    "11": 103,
    "00": 94
  },
  {
    "10": 107,
    "00": 309,
    "11": 473,
    "01": 111
  },
  {
    "10": 206,
    "00": 207,
    "11": 276,
    "01": 311
  },
  {
    "11": 309,
    "00": 182,
    "01": 300,
    "10": 209
  },
  {
    "00": 312,
    "11": 197,
    "01": 290,
    "10": 201
  },
  {
    "10": 310,
    "01": 220,
    "00": 196,
    "11": 274
  },
  {
    "11": 337,
    "00": 408,
    "10": 114,
    "01": 141
  },
  {
    "00": 200,
    "10": 283,
    "11": 213,
    "01": 304
  },
  {
    "10": 171,
    "11": 194,
    "00": 334,
    "01": 301
  },
  {
    "01": 226,
    "00": 185,
    "10": 303,
    "11": 286
  },
  {
    "01": 288,
    "11": 201,
    "10": 283,
    "00": 228
  },
  {
    "10": 341,
    "00": 129,
    "01": 399,
    "11": 131
  },
  {
    "11": 187,
    "00": 556,
    "01": 114,
    "10": 143
  },
  {
    "10": 580,
    "11": 109,
    "00": 126,
    "01": 185
  },
  {
    "00": 344,
    "11": 145,
    "01": 148,
    "10": 363
  },
  {
    "11": 158,
    "10": 335,
    "00": 342,
    "01": 165
  },
  {
    "10": 196,
    "00": 146,
    "01": 539,
    "11": 119
  },
  {
    "11": 541,
    "01": 129,
    "00": 190,
    "10": 140
  },
  {
    "01": 329,
    "11": 351,
    "00": 148,
    "10": 172
  },
  {
    "01": 329,
    "10": 161,
    "00": 166,
    "11": 344
  },
  {
    "10": 154,
    "01": 349,
    "11": 135,
    "00": 362
  },
  {
    "00": 155,
    "11": 342,
    "10": 333,
    "01": 170
  },
  {
    "00": 312,
    "10": 205,
    "11": 276,
    "01": 207
  },
  {
    "11": 220,
    "10": 287,
    "00": 232,
    "01": 261
  },
  {
    "01": 341,
    "00": 349,
    "11": 159,
    "10": 151
  },
  {
    "00": 172,
    "10": 319,
    "11": 355,
    "01": 154
  },
  {
    "10": 289,
    "00": 218,
    "11": 199,
    "01": 294
  },
  {
    "10": 272,
    "11": 200,
    "01": 288,
    "00": 240
  },
  {
    "10": 122,
    "01": 97,
    "00": 710,
    "11": 71
  },
  {
    "00": 130,
    "01": 73,
    "10": 685,
    "11": 112
  },
  {
    "01": 105,
    "11": 74,
    "00": 408,
    "10": 413
  },
  {
    "00": 395,
    "10": 427,
    "11": 79,
    "01": 99
  },
  {
    "01": 653,
    "11": 135,
    "10": 91,
    "00": 121
  },
  {
    "11": 640,
    "01": 146,
    "10": 118,
    "00": 96
  },
  {
    "00": 121,
    "01": 398,
    "11": 369,
    "10": 112
  },
  {
    "11": 385,
    "10": 105,
    "01": 412,
    "00": 98
  },
  {
    "10": 97,
    "00": 413,
    "01": 402,
    "11": 88
  },
  {
    "10": 403,
    "01": 114,
    "11": 366,
    "00": 117
  },
  {
    "10": 257,
    "01": 247,
    "00": 245,
    "11": 251
  },
  {
    "01": 269,
    "00": 250,
    "11": 233,
    "10": 248
  },
  {
    "00": 377,
    "10": 119,
    "01": 389,
    "11": 115
  },
  {
    "11": 388,
    "10": 387,
    "01": 108,
    "00": 117
  },
  {
    "01": 247,
    "11": 240,
    "00": 261,
    "10": 252
  },
  {
    "01": 258,
    "11": 228,
    "10": 265,
    "00": 249
  }
]